pyvsapm.cpython-312-darwin.so
libvsapm_python-20240503.dist-info/METADATA
libvsapm_python-20240503.dist-info/WHEEL
libvsapm_python-20240503.dist-info/top_level.txt
libvsapm_python-20240503.dist-info/RECORD
